fastapi_jinja_utils/__init__.py
fastapi_jinja_utils-1.0.dist-info/WHEEL
fastapi_jinja_utils-1.0.dist-info/METADATA
fastapi_jinja_utils-1.0.dist-info/RECORD
