Metadata-Version: 2.1
Name: fastapi-jinja-utils
Version: 1.0
Summary: 
Author: Tyler M Kontra
Author-email: tyler@tylerkontra.com
Requires-Python: >=3.7,<4
Classifier: Programming Language :: Python :: 3
Classifier: Programming Language :: Python :: 3.10
Classifier: Programming Language :: Python :: 3.7
Classifier: Programming Language :: Python :: 3.8
Classifier: Programming Language :: Python :: 3.9
Requires-Dist: Jinja2 (>=3.1.2,<4.0.0)
Requires-Dist: fastapi (>=0.78.0,<0.79.0)
